{
"lowlevel": {
    "average_loudness": 0.752347230911,
    "barkbands_crest": {
        "dmean": 2.78337407112,
        "dmean2": 4.42110109329,
        "dvar": 7.71715974808,
        "dvar2": 18.0581436157,
        "max": 26.9081840515,
        "mean": 10.7896966934,
        "median": 9.5586271286,
        "min": 2.90951728821,
        "var": 24.8686904907
    },
    "barkbands_flatness_db": {
        "dmean": 0.026762990281,
        "dmean2": 0.0396175757051,
        "dvar": 0.00104963034391,
        "dvar2": 0.00215296493843,
        "max": 0.712187707424,
        "mean": 0.152997910976,
        "median": 0.12872107327,
        "min": 0.0225730482489,
        "var": 0.00785687565804
    },
    "barkbands_kurtosis": {
        "dmean": 12.6694097519,
        "dmean2": 22.5603103638,
        "dvar": 162122.71875,
        "dvar2": 486334.53125,
        "max": 25779.6015625,
        "mean": 11.941947937,
        "median": 2.69089174271,
        "min": -1.90973675251,
        "var": 81559.2265625
    },
    "barkbands_skewness": {
        "dmean": 0.764776229858,
        "dmean2": 1.17325556278,
        "dvar": 5.09033727646,
        "dvar2": 14.5269050598,
        "max": 132.160354614,
        "mean": 1.78818535805,
        "median": 1.47790980339,
        "min": -6.84620380402,
        "var": 5.48123979568
    },
    "barkbands_spread": {
        "dmean": 5.46860742569,
        "dmean2": 8.50515556335,
        "dvar": 63.6224861145,
        "dvar2": 146.061309814,
        "max": 110.801597595,
        "mean": 19.3092212677,
        "median": 17.8614463806,
        "min": 0.0111988056451,
        "var": 179.231414795
    },
    "dissonance": {
        "dmean": 0.0235261451453,
        "dmean2": 0.039182100445,
        "dvar": 0.000856825907249,
        "dvar2": 0.00221371883526,
        "max": 0.500000059605,
        "mean": 0.451171934605,
        "median": 0.466897785664,
        "min": 0.0550577826798,
        "var": 0.00270333350636
    },
    "dynamic_complexity": 6.64335536957,
    "erbbands_crest": {
        "dmean": 2.56855773926,
        "dmean2": 4.17998838425,
        "dvar": 6.50472545624,
        "dvar2": 16.2384471893,
        "max": 31.5820541382,
        "mean": 9.30548000336,
        "median": 7.98648691177,
        "min": 2.1064889431,
        "var": 23.3247509003
    },
    "erbbands_flatness_db": {
        "dmean": 0.0192463863641,
        "dmean2": 0.0270072054118,
        "dvar": 0.000566447793972,
        "dvar2": 0.00100292486604,
        "max": 0.600561797619,
        "mean": 0.159426882863,
        "median": 0.136626154184,
        "min": 0.0341951958835,
        "var": 0.00558608165011
    },
    "erbbands_kurtosis": {
        "dmean": 1.79312157631,
        "dmean2": 2.77934288979,
        "dvar": 20.6914272308,
        "dvar2": 47.2109298706,
        "max": 147.601013184,
        "mean": 2.12673068047,
        "median": 0.251899957657,
        "min": -1.79815685749,
        "var": 46.7251243591
    },
    "erbbands_skewness": {
        "dmean": 0.42078858614,
        "dmean2": 0.628030061722,
        "dvar": 0.273009747267,
        "dvar2": 0.580979049206,
        "max": 7.33804559708,
        "mean": 0.578461825848,
        "median": 0.512656033039,
        "min": -7.12215185165,
        "var": 1.04621326923
    },
    "erbbands_spread": {
        "dmean": 8.22418785095,
        "dmean2": 12.5386981964,
        "dvar": 111.403816223,
        "dvar2": 251.307281494,
        "max": 159.571655273,
        "mean": 36.2912979126,
        "median": 34.2141571045,
        "min": 0.463749200106,
        "var": 449.432830811
    },
    "hfc": {
        "dmean": 5.15898752213,
        "dmean2": 7.16503620148,
        "dvar": 100.350730896,
        "dvar2": 200.856124878,
        "max": 273.942779541,
        "mean": 18.523223877,
        "median": 12.2851772308,
        "min": 1.11601011254e-16,
        "var": 430.565612793
    },
    "melbands_crest": {
        "dmean": 3.50457668304,
        "dmean2": 5.52077579498,
        "dvar": 12.2952785492,
        "dvar2": 27.4467163086,
        "max": 39.9765281677,
        "mean": 14.9356737137,
        "median": 13.3765277863,
        "min": 1.61248862743,
        "var": 46.2416801453
    },
    "melbands_flatness_db": {
        "dmean": 0.0305876526982,
        "dmean2": 0.044469024986,
        "dvar": 0.00132870592643,
        "dvar2": 0.00255801621825,
        "max": 0.706086933613,
        "mean": 0.225001975894,
        "median": 0.198737218976,
        "min": 0.00324530107901,
        "var": 0.0107366917655
    },
    "melbands_kurtosis": {
        "dmean": 19.9456062317,
        "dmean2": 34.62134552,
        "dvar": 306118.09375,
        "dvar2": 918131.3125,
        "max": 35423.90625,
        "mean": 23.4721908569,
        "median": 7.45733070374,
        "min": -1.90600311756,
        "var": 154571.9375
    },
    "melbands_skewness": {
        "dmean": 0.919103562832,
        "dmean2": 1.40941894054,
        "dvar": 8.2279176712,
        "dvar2": 23.6834106445,
        "max": 172.514709473,
        "mean": 2.6610224247,
        "median": 2.20713639259,
        "min": -4.25718212128,
        "var": 8.43892383575
    },
    "melbands_spread": {
        "dmean": 6.70101547241,
        "dmean2": 10.4223985672,
        "dvar": 167.143753052,
        "dvar2": 346.183380127,
        "max": 259.957763672,
        "mean": 21.0071163177,
        "median": 16.4028968811,
        "min": 0.0187053736299,
        "var": 478.10635376
    },
    "pitch_salience": {
        "dmean": 0.0791936889291,
        "dmean2": 0.124217517674,
        "dvar": 0.00593594415113,
        "dvar2": 0.0134865855798,
        "max": 0.957773447037,
        "mean": 0.545996487141,
        "median": 0.569468796253,
        "min": 0.00500360317528,
        "var": 0.0226186048239
    },
    "silence_rate_20dB": {
        "dmean": 0,
        "dmean2": 0,
        "dvar": 0,
        "dvar2": 0,
        "max": 1,
        "mean": 1,
        "median": 1,
        "min": 1,
        "var": 0
    },
    "silence_rate_30dB": {
        "dmean": 0.0416463725269,
        "dmean2": 0.083302885294,
        "dvar": 0.0399142056704,
        "dvar2": 0.0797736123204,
        "max": 1,
        "mean": 0.922196507454,
        "median": 1,
        "min": 0,
        "var": 0.0717457532883
    },
    "silence_rate_60dB": {
        "dmean": 0.0289819780737,
        "dmean2": 0.0579710155725,
        "dvar": 0.0281413383782,
        "dvar2": 0.0602095685899,
        "max": 1,
        "mean": 0.277365148067,
        "median": 0,
        "min": 0,
        "var": 0.20041719079
    },
    "spectral_centroid": {
        "dmean": 223.867645264,
        "dmean2": 332.86907959,
        "dvar": 113127.359375,
        "dvar2": 195075.703125,
        "max": 11430.9658203,
        "mean": 1196.0949707,
        "median": 1114.52856445,
        "min": 117.85093689,
        "var": 596205.375
    },
    "spectral_complexity": {
        "dmean": 2.81222605705,
        "dmean2": 4.14395332336,
        "dvar": 14.0032939911,
        "dvar2": 23.9444961548,
        "max": 60,
        "mean": 15.2474126816,
        "median": 13,
        "min": 0,
        "var": 161.197265625
    },
    "spectral_decrease": {
        "dmean": 2.82906098548e-09,
        "dmean2": 4.4194701232e-09,
        "dvar": 3.72975638938e-17,
        "dvar2": 8.30850051925e-17,
        "max": 8.20010896142e-29,
        "mean": -7.94619747779e-09,
        "median": -4.59460292035e-09,
        "min": -7.31956717459e-08,
        "var": 1.09622170236e-16
    },
    "spectral_energy": {
        "dmean": 0.0109602157027,
        "dmean2": 0.0170611273497,
        "dvar": 0.000542059657164,
        "dvar2": 0.00120284035802,
        "max": 0.277755260468,
        "mean": 0.0316708944738,
        "median": 0.0187490582466,
        "min": 9.97711327532e-21,
        "var": 0.00165337813087
    },
    "spectral_energyband_high": {
        "dmean": 0.000327907939209,
        "dmean2": 0.000454683788121,
        "dvar": 8.5718278342e-07,
        "dvar2": 1.77864581019e-06,
        "max": 0.0417880862951,
        "mean": 0.000837411382236,
        "median": 0.000393804657506,
        "min": 7.29904899531e-21,
        "var": 1.97965164261e-06
    },
    "spectral_energyband_low": {
        "dmean": 0.00881857424974,
        "dmean2": 0.0140545107424,
        "dvar": 0.00052261701785,
        "dvar2": 0.00117306096945,
        "max": 0.274382770061,
        "mean": 0.0165850911289,
        "median": 0.00418771710247,
        "min": 4.16859882293e-23,
        "var": 0.00113177811727
    },
    "spectral_energyband_middle_high": {
        "dmean": 0.0013535640901,
        "dmean2": 0.00207867450081,
        "dvar": 5.81687618251e-06,
        "dvar2": 1.34245783556e-05,
        "max": 0.0390093401074,
        "mean": 0.00415119342506,
        "median": 0.00166885228828,
        "min": 1.37721947016e-21,
        "var": 2.8435346394e-05
    },
    "spectral_energyband_middle_low": {
        "dmean": 0.00391836976632,
        "dmean2": 0.00616407766938,
        "dvar": 4.97267392348e-05,
        "dvar2": 0.000120464166685,
        "max": 0.0933585762978,
        "mean": 0.0109727438539,
        "median": 0.00805908348411,
        "min": 1.74719942514e-22,
        "var": 0.000138675386552
    },
    "spectral_entropy": {
        "dmean": 0.178925335407,
        "dmean2": 0.255186617374,
        "dvar": 0.0677819848061,
        "dvar2": 0.121427573264,
        "max": 9.81216526031,
        "mean": 7.45826005936,
        "median": 7.67114877701,
        "min": 3.51333379745,
        "var": 0.555336713791
    },
    "spectral_flux": {
        "dmean": 0.0254030041397,
        "dmean2": 0.0405775904655,
        "dvar": 0.00158753350843,
        "dvar2": 0.00376979913563,
        "max": 0.44805252552,
        "mean": 0.0752766281366,
        "median": 0.0615615695715,
        "min": 6.62236585014e-11,
        "var": 0.00437467359006
    },
    "spectral_kurtosis": {
        "dmean": 2.79539823532,
        "dmean2": 4.21078920364,
        "dvar": 56.394077301,
        "dvar2": 107.290534973,
        "max": 261.544555664,
        "mean": 7.7373623848,
        "median": 3.66301107407,
        "min": -1.23420548439,
        "var": 252.19291687
    },
    "spectral_rms": {
        "dmean": 0.000771269726101,
        "dmean2": 0.00115195766557,
        "dvar": 1.45371711824e-06,
        "dvar2": 2.84043790089e-06,
        "max": 0.0164614915848,
        "mean": 0.00449832109734,
        "median": 0.00427688704804,
        "min": 3.1198988705e-12,
        "var": 1.06636198325e-05
    },
    "spectral_rolloff": {
        "dmean": 445.177124023,
        "dmean2": 732.97644043,
        "dvar": 1123696.75,
        "dvar2": 2421108.75,
        "max": 19379.8828125,
        "mean": 1284.41149902,
        "median": 818.26171875,
        "min": 21.533203125,
        "var": 2889694.25
    },
    "spectral_skewness": {
        "dmean": 0.277101963758,
        "dmean2": 0.407363027334,
        "dvar": 0.219049274921,
        "dvar2": 0.394525289536,
        "max": 13.6604394913,
        "mean": 1.89827895164,
        "median": 1.57569217682,
        "min": -0.232982292771,
        "var": 1.56821775436
    },
    "spectral_spread": {
        "dmean": 590930.9375,
        "dmean2": 844297.125,
        "dvar": 950199451648,
        "dvar2": 1.74933200077e+12,
        "max": 42499972,
        "mean": 4993560,
        "median": 5010145,
        "min": 466668.90625,
        "var": 5.49317142118e+12
    },
    "spectral_strongpeak": {
        "dmean": 0.376636713743,
        "dmean2": 0.633396804333,
        "dvar": 0.486725270748,
        "dvar2": 1.23669230938,
        "max": 10.9856948853,
        "mean": 0.663143575191,
        "median": 0.356651157141,
        "min": 0,
        "var": 0.758281707764
    },
    "zerocrossingrate": {
        "dmean": 0.0111557878554,
        "dmean2": 0.0124904494733,
        "dvar": 0.000280373526039,
        "dvar2": 0.000288413837552,
        "max": 0.72802734375,
        "mean": 0.0573408529162,
        "median": 0.0498046875,
        "min": 0,
        "var": 0.00219731079414
    },
    "barkbands": {
        "dmean": [0.00069712754339, 0.00717907259241, 0.00247935578227, 0.00133593636565, 0.00145938014612, 0.000840945227537, 0.000742876320146, 0.000902720435988, 0.000940789410379, 0.000301334745018, 0.000261376961134, 0.000330664741341, 0.000390269327909, 0.000308078102535, 0.000223001057748, 0.000168230661075, 0.000214035098907, 0.000131094930111, 0.000120504919323, 9.36762517085e-05, 8.01205969765e-05, 8.37687694002e-05, 6.91417371854e-05, 5.36234365427e-05, 4.66771452921e-05, 3.17151607305e-05, 8.52480388858e-06],
        "dmean2": [0.0010273011867, 0.0109597910196, 0.00425830995664, 0.0023229632061, 0.00239965505898, 0.00134929805063, 0.00118908262812, 0.00136298930738, 0.00146907370072, 0.000483470183099, 0.000428356433986, 0.000522892631125, 0.000641418737359, 0.0005039126263, 0.000361353246262, 0.000270290212939, 0.000341889215633, 0.000206155586056, 0.000191192113562, 0.000148038438056, 0.000123035002616, 0.000124475525809, 0.000105098297354, 8.06704410934e-05, 6.64982726448e-05, 4.40744661319e-05, 1.18935258797e-05],
        "dvar": [3.98216343456e-06, 0.00040396588156, 7.49577811803e-05, 1.51865797307e-05, 9.67144478636e-06, 2.89727427116e-06, 2.01344550987e-06, 3.68260225514e-06, 4.45594150733e-06, 4.23358102353e-07, 4.33284071732e-07, 5.76292109145e-07, 9.94289280243e-07, 5.61627985007e-07, 4.55417250578e-07, 3.20820475963e-07, 1.9485932512e-07, 9.92798092625e-08, 6.2478797247e-08, 5.65510163142e-08, 5.03126322826e-08, 4.93095875242e-08, 1.15434339421e-07, 1.80717396603e-08, 1.19374590213e-08, 7.16203230056e-09, 7.33942240316e-10],
        "dvar2": [6.70466215524e-06, 0.000843640358653, 0.000204774943995, 4.16154907725e-05, 2.62121993728e-05, 7.3680503192e-06, 5.27631664227e-06, 8.1945936472e-06, 1.06640291051e-05, 1.06530728772e-06, 1.11420808935e-06, 1.39105293329e-06, 2.67809468824e-06, 1.42015073834e-06, 1.06094057628e-06, 8.80699587924e-07, 4.71285602544e-07, 2.35003128068e-07, 1.43857704415e-07, 1.35530726197e-07, 1.21000184095e-07, 1.07231869606e-07, 2.80719291368e-07, 3.86495528915e-08, 2.39833539695e-08, 1.49196317523e-08, 1.49649359571e-09],
        "max": [0.0277719330043, 0.254573822021, 0.106217876077, 0.0431719794869, 0.0619010031223, 0.0289482530206, 0.0219727326185, 0.0398849286139, 0.034029122442, 0.0209351982921, 0.0128457387909, 0.0149311423302, 0.0189487859607, 0.016008971259, 0.0244205370545, 0.0172576159239, 0.00923073850572, 0.00572974979877, 0.0045007201843, 0.0101118711755, 0.0087651386857, 0.00856809597462, 0.0161838252097, 0.00402125390247, 0.00167933863122, 0.00126563559752, 0.000450547813671],
        "mean": [0.000997695606202, 0.0118688875809, 0.00295539409854, 0.00173038546927, 0.00279063964263, 0.00161251064856, 0.00134558591526, 0.00169681035914, 0.00164675631095, 0.000527167983819, 0.000387516600313, 0.000548437528778, 0.000631794449873, 0.000486357312184, 0.000357880489901, 0.000266125309281, 0.000387954234611, 0.00024545044289, 0.000244662922341, 0.000192137857084, 0.000162212891155, 0.000184293385246, 0.000134130983497, 0.000113917980343, 9.19620142668e-05, 5.33547718078e-05, 1.08719505079e-05],
        "median": [7.86844320828e-05, 0.00182629737537, 0.00069819309283, 0.000405823928304, 0.00142230419442, 0.000644179817755, 0.000431544380262, 0.000325536588207, 0.000460743234726, 0.000158115377417, 9.14277261472e-05, 0.000110348795715, 9.38801531447e-05, 8.93629403436e-05, 7.07066355972e-05, 6.23116357019e-05, 8.22061265353e-05, 4.52725325886e-05, 6.24469030299e-05, 4.59955699625e-05, 5.48965545022e-05, 6.95026246831e-05, 4.7293247917e-05, 3.9943271986e-05, 3.34499018209e-05, 1.49044544742e-05, 9.10837854917e-07],
        "min": [4.07183099118e-24, 7.2201409429e-24, 2.53426575069e-24, 6.07730749988e-25, 1.00825069603e-23, 1.84956469833e-23, 1.24054104476e-23, 1.54541543202e-23, 4.18878324914e-23, 3.30398770706e-23, 3.17887342086e-23, 4.9676066882e-23, 3.41422407659e-23, 4.19009181161e-23, 7.6539570117e-23, 7.90463555036e-23, 1.53332635953e-22, 1.20260115818e-22, 1.79976532933e-22, 2.55851875857e-22, 3.31809891404e-22, 3.32148281178e-22, 4.44768462144e-22, 6.37691426845e-22, 1.03329701715e-21, 1.54445353921e-21, 2.12307677803e-21],
        "var": [7.54393022362e-06, 0.000790830992628, 6.22438383289e-05, 1.39591647894e-05, 1.5942430764e-05, 5.61134538657e-06, 4.50238530902e-06, 1.09880065793e-05, 9.75050897978e-06, 1.01095054106e-06, 7.45360694054e-07, 1.34738195356e-06, 2.1406290216e-06, 1.11536621716e-06, 7.38553978863e-07, 4.89205319809e-07, 4.5715907504e-07, 2.31841298159e-07, 1.62573087437e-07, 1.1272688738e-07, 9.04750763198e-08, 1.06813438094e-07, 1.72385938413e-07, 3.89005734291e-08, 2.73163216491e-08, 1.27160202368e-08, 1.11564690819e-09]
    },
    "erbbands": {
        "dmean": [0.326315701008, 1.31742691994, 2.61962509155, 3.7764954567, 4.67188549042, 5.46446228027, 5.77685546875, 7.96691846848, 8.03870773315, 15.449590683, 18.3593921661, 19.4219779968, 13.369058609, 10.1416654587, 10.9471130371, 10.508234024, 13.9938097, 15.15163517, 13.2382917404, 9.55795192719, 9.46426963806, 11.8091611862, 7.60926389694, 5.28256797791, 5.83741760254, 4.17497873306, 3.49594902992, 3.10028481483, 3.12549877167, 2.4333126545, 2.10583972931, 1.19491291046, 0.949408710003, 0.604623198509, 0.294097483158, 0.145216330886, 0.0589982606471, 0.0126801626757, 0.0016338143032, 6.1687984271e-05],
        "dmean2": [0.445175379515, 2.17347812653, 4.44201803207, 6.60541629791, 7.83723211288, 9.2028169632, 9.3907995224, 12.6650838852, 12.9823646545, 23.7592639923, 28.2252082825, 30.7505016327, 20.4392757416, 16.4012317657, 17.2688274384, 16.983259201, 22.9753952026, 24.6226997375, 21.3077106476, 15.4602775574, 14.8895149231, 18.9193172455, 11.9340763092, 8.21506881714, 9.29356193542, 6.55039739609, 5.37790489197, 4.73698043823, 4.67240142822, 3.67756891251, 3.19288134575, 1.79892992973, 1.43831372261, 0.895785629749, 0.416684150696, 0.20915260911, 0.0827888697386, 0.0174605287611, 0.00227426923811, 8.65129259182e-05],
        "dvar": [1.00307428837, 11.8941440582, 72.5717086792, 160.855285645, 103.568077087, 177.566467285, 135.261169434, 280.27142334, 280.488372803, 862.141906738, 1583.10717773, 2000.06750488, 785.942199707, 631.493286133, 586.457580566, 741.912353516, 1156.05175781, 1314.71228027, 1414.43859863, 566.262023926, 1010.33538818, 590.364196777, 315.042053223, 144.217971802, 140.158828735, 139.609573364, 104.315437317, 65.9980621338, 64.9422836304, 77.2018127441, 118.115226746, 16.4179058075, 4.65654468536, 1.99127209187, 0.49793151021, 0.132948964834, 0.0283113829792, 0.00137251836713, 2.72878987744e-05, 3.31190577185e-08],
        "dvar2": [1.81072020531, 30.6426620483, 197.095855713, 443.694396973, 272.176208496, 505.170684814, 361.983581543, 703.634216309, 742.749023438, 2108.04760742, 3810.64379883, 4940.58447266, 1813.37573242, 1617.36999512, 1411.88562012, 1917.16784668, 3126.75, 3282.65576172, 3361.30712891, 1431.89379883, 2693.53320312, 1424.68005371, 745.583312988, 318.208404541, 332.312042236, 326.877044678, 253.373855591, 148.391448975, 137.185714722, 186.491470337, 288.736175537, 36.3169326782, 10.409198761, 4.24316835403, 0.981397032738, 0.277925431728, 0.0610124506056, 0.0027693149168, 5.61566448596e-05, 6.83492729081e-08],
        "max": [12.992814064, 37.9842376709, 111.689239502, 133.423324585, 138.104309082, 279.0105896, 194.137619019, 315.177246094, 403.967468262, 400.677886963, 698.288574219, 698.729370117, 516.274047852, 633.105529785, 499.388824463, 593.846252441, 774.649230957, 884.781494141, 928.503417969, 478.746551514, 1013.84429932, 486.74041748, 386.445953369, 185.750961304, 217.902740479, 594.551879883, 480.519958496, 229.773117065, 315.415039062, 367.028137207, 528.984680176, 164.171875, 41.6644592285, 23.1978397369, 10.7154188156, 5.68540859222, 2.6701271534, 0.577394247055, 0.0850412771106, 0.00305153662339],
        "mean": [0.46778100729, 2.12232494354, 3.66965198517, 4.68313598633, 7.47798490524, 9.28988742828, 10.8252038956, 15.3923692703, 15.7577028275, 29.1234741211, 35.5064811707, 34.2309417725, 25.7291908264, 17.5457897186, 18.7778701782, 18.5961723328, 23.9300899506, 26.6809329987, 21.7580051422, 16.9966278076, 16.8207969666, 22.7638473511, 15.2930669785, 10.917848587, 12.3236064911, 8.73801136017, 6.99120569229, 6.52039909363, 6.74092006683, 4.90302991867, 3.93868494034, 2.37698292732, 1.95724666119, 1.18626976013, 0.557096481323, 0.253380089998, 0.0931567624211, 0.0192177873105, 0.00210466957651, 0.00010590707825],
        "median": [0.033339548856, 0.378062427044, 1.00245499611, 1.3741710186, 2.82455945015, 4.55161094666, 4.69529771805, 5.48425960541, 7.11999702454, 9.62086296082, 9.96467494965, 10.2352275848, 8.18519973755, 5.60374116898, 4.82797241211, 4.22456598282, 4.85003423691, 5.74982070923, 4.76312017441, 3.92571210861, 4.45557022095, 4.73461103439, 3.06025409698, 2.7107758522, 3.12794280052, 2.23249483109, 1.89710485935, 2.43400216103, 2.55586528778, 1.6704158783, 1.35055422783, 0.848538517952, 0.662571907043, 0.426417738199, 0.192654788494, 0.0755041986704, 0.0220276471227, 0.00336417322978, 0.00020378503541, 3.7121004425e-05],
        "min": [1.52189254646e-22, 1.83533364129e-21, 4.16562219199e-21, 4.34638256236e-21, 2.34281864061e-20, 4.28826908536e-20, 1.2590395904e-19, 1.0719254551e-19, 1.12132746009e-19, 2.96754560271e-19, 5.22476949993e-19, 9.44516285841e-19, 6.91801441768e-19, 1.36681380544e-18, 1.87085713888e-18, 2.05442113131e-18, 1.85721382865e-18, 2.38684847588e-18, 4.31559233441e-18, 4.6240620469e-18, 6.17241428625e-18, 7.83647420403e-18, 6.6083922358e-18, 7.97855736349e-18, 6.86381320125e-18, 1.18914194459e-17, 1.38893187056e-17, 1.15544773495e-17, 9.87405662641e-18, 1.70532828942e-17, 1.2125588487e-17, 1.23314059127e-17, 9.81596207763e-18, 9.50517956814e-18, 7.70673671522e-18, 4.81108675622e-18, 2.62451773179e-18, 1.08096996424e-18, 2.69722168606e-19, 3.02520209473e-20],
        "var": [1.85104465485, 20.0471458435, 67.8417663574, 123.702514648, 150.715667725, 226.78288269, 254.926193237, 572.015991211, 554.731384277, 2155.74682617, 3990.04711914, 4120.62792969, 2016.97998047, 1291.75317383, 1295.62915039, 1674.65429688, 2398.99731445, 3116.89501953, 2228.3996582, 1221.76074219, 1602.91394043, 1516.41369629, 817.75604248, 381.813873291, 367.783538818, 262.47277832, 179.006240845, 130.65196228, 142.995834351, 119.075805664, 172.990264893, 27.0060539246, 10.8085956573, 4.39668941498, 1.10175096989, 0.248449161649, 0.0455476418138, 0.00243123038672, 4.08303167205e-05, 5.60866766364e-08]
    },
    "gfcc": {
        "mean": [-55.6784362793, 90.3661422729, -101.869728088, 21.6226463318, -59.1714172363, 12.0957965851, -33.7653045654, 9.29168510437, -18.3838005066, 4.02508640289, -16.6408119202, -0.501778781414, -11.5283994675],
        "cov": [[26349.8945312, -3020.39013672, 159.283981323, 1493.56958008, -312.123168945, 415.263336182, -608.87701416, 699.347961426, -102.399986267, 685.088256836, -156.695053101, 505.617675781, -393.34262085], [-3020.39013672, 2123.62158203, 90.2834701538, -219.521438599, 310.48059082, -112.262199402, 284.822235107, -177.298812866, 87.4219055176, -245.039474487, 129.535751343, -196.177780151, 114.719566345], [159.283981323, 90.2834701538, 1524.50866699, 275.649719238, 172.90574646, 63.5361976624, -49.1118354797, 15.4345264435, -136.210769653, -26.4015674591, -134.711013794, -49.0049057007, -7.78255033493], [1493.56958008, -219.521438599, 275.649719238, 662.86529541, 152.534881592, 109.119796753, -26.3231143951, 43.4552574158, 37.4738502502, 48.8993301392, 27.7112674713, 24.1368732452, 13.6686010361], [-312.123168945, 310.48059082, 172.90574646, 152.534881592, 407.078216553, 76.6257019043, 114.552955627, 22.4737510681, 22.4888439178, 13.0297269821, 51.5368995667, -21.8164825439, 17.4737968445], [415.263336182, -112.262199402, 63.5361976624, 109.119796753, 76.6257019043, 212.961013794, 91.8180847168, 58.7473106384, 13.1250963211, 55.2456283569, 13.2296714783, 35.9495697021, -9.82193851471], [-608.87701416, 284.822235107, -49.1118354797, -26.3231143951, 114.552955627, 91.8180847168, 337.18951416, 53.3898696899, 28.5604724884, 10.6303634644, 68.5376968384, 18.8307800293, 22.6318836212], [699.347961426, -177.298812866, 15.4345264435, 43.4552574158, 22.4737510681, 58.7473106384, 53.3898696899, 178.300109863, 37.2926673889, 57.4573287964, -14.0810136795, 37.5812721252, -7.92888832092], [-102.399986267, 87.4219055176, -136.210769653, 37.4738502502, 22.4888439178, 13.1250963211, 28.5604724884, 37.2926673889, 152.155944824, 20.5293960571, 30.7288570404, -1.69108831882, 22.1632118225], [685.088256836, -245.039474487, -26.4015674591, 48.8993301392, 13.0297269821, 55.2456283569, 10.6303634644, 57.4573287964, 20.5293960571, 179.541397095, 44.1063728333, 75.1147537231, -8.48150730133], [-156.695053101, 129.535751343, -134.711013794, 27.7112674713, 51.5368995667, 13.2296714783, 68.5376968384, -14.0810136795, 30.7288570404, 44.1063728333, 144.870651245, 44.786026001, 25.3400440216], [505.617675781, -196.177780151, -49.0049057007, 24.1368732452, -21.8164825439, 35.9495697021, 18.8307800293, 37.5812721252, -1.69108831882, 75.1147537231, 44.786026001, 151.483963013, 25.1799488068], [-393.34262085, 114.719566345, -7.78255033493, 13.6686010361, 17.4737968445, -9.82193851471, 22.6318836212, -7.92888832092, 22.1632118225, -8.48150730133, 25.3400440216, 25.1799488068, 96.0232009888]],
        "icov": [[6.39873323962e-05, -1.78415502887e-05, 3.23024069075e-05, -0.00015571975382, 6.15534590906e-05, -2.34340950556e-05, 0.000114286107419, -0.000205590025871, 0.000107642204966, -0.000113748457807, 6.85010745656e-05, -0.000152350432472, 0.000237683561863], [-1.78415502887e-05, 0.00116281374358, -0.000260893080849, 0.000522362766787, -0.000653236114886, 0.000440776522737, -0.000776296656113, 0.00077635247726, -0.000819658627734, 0.00107789575122, -0.00108938978519, 0.00102155690547, -0.000842779350933], [3.23024069075e-05, -0.000260893080849, 0.00100114324596, -0.000542962865438, -0.000216583663132, -0.00018226983957, 0.000242965237703, -0.000312882912112, 0.00109930743929, -0.000397440773668, 0.00117851467803, -0.000109754015284, -3.09500901494e-05], [-0.00015571975382, 0.000522362766787, -0.000542962865438, 0.00262677762657, -0.000942385580856, -0.000701337237842, 0.000197491637664, 0.000557034392841, -0.00119095481932, 0.000731344392989, -0.00126447970979, 0.000646970351227, -0.00107714859769], [6.15534590906e-05, -0.000653236114886, -0.000216583663132, -0.000942385580856, 0.00383539218456, -0.000810509140138, -0.000333966774633, -0.000745879136957, 0.000405544007663, -0.000774217129219, -0.000634738360532, 0.000534341903403, 0.000250831682933], [-2.34340950556e-05, 0.000440776522737, -0.00018226983957, -0.000701337237842, -0.000810509140138, 0.00704518798739, -0.00217308942229, -0.000279320141999, -0.000411802524468, -0.000812413985841, 0.000579992192797, -0.00066427490674, 0.000864131667186], [0.000114286107419, -0.000776296656113, 0.000242965237703, 0.000197491637664, -0.000333966774633, -0.00217308942229, 0.00517321657389, -0.00223623332568, 0.000731341890059, 0.000116950097436, -0.00136886641849, -0.000637322315015, 0.000191626677406], [-0.000205590025871, 0.00077635247726, -0.000312882912112, 0.000557034392841, -0.000745879136957, -0.000279320141999, -0.00223623332568, 0.00914236716926, -0.00295800226741, -0.000904375454411, 0.00208289455622, -0.000688182364684, -0.000251544144703], [0.000107642204966, -0.000819658627734, 0.00109930743929, -0.00119095481932, 0.000405544007663, -0.000411802524468, 0.000731341890059, -0.00295800226741, 0.00944149401039, -0.00159776653163, -0.000261710287305, 0.00113172119018, -0.00140175898559], [-0.000113748457807, 0.00107789575122, -0.000397440773668, 0.000731344392989, -0.000774217129219, -0.000812413985841, 0.000116950097436, -0.000904375454411, -0.00159776653163, 0.00978249777108, -0.00350461294875, -0.00214127660729, 0.000784710049629], [6.85010745656e-05, -0.00108938978519, 0.00117851467803, -0.00126447970979, -0.000634738360532, 0.000579992192797, -0.00136886641849, 0.00208289455622, -0.000261710287305, -0.00350461294875, 0.012562119402, -0.00359578523785, -9.42459955695e-05], [-0.000152350432472, 0.00102155690547, -0.000109754015284, 0.000646970351227, 0.000534341903403, -0.00066427490674, -0.000637322315015, -0.000688182364684, 0.00113172119018, -0.00214127660729, -0.00359578523785, 0.0116777429357, -0.004580990877], [0.000237683561863, -0.000842779350933, -3.09500901494e-05, -0.00107714859769, 0.000250831682933, 0.000864131667186, 0.000191626677406, -0.000251544144703, -0.00140175898559, 0.000784710049629, -9.42459955695e-05, -0.004580990877, 0.0141412699595]]
    },
    "melbands": {
        "dmean": [0.0023207126651, 0.00132763385773, 0.000668269000016, 0.00034060201142, 0.000210872123716, 0.000170835774043, 0.000131293854793, 0.000182060757652, 0.000152177424752, 0.000130527856527, 6.9413195888e-05, 4.14814130636e-05, 3.69038170902e-05, 3.44620166288e-05, 2.94961537293e-05, 3.69843801309e-05, 2.91492960969e-05, 2.49838176387e-05, 1.82947314897e-05, 1.16372721095e-05, 1.06756569949e-05, 1.42323051477e-05, 1.00249772004e-05, 6.20212676949e-06, 4.65901439384e-06, 4.90667162012e-06, 4.1480057007e-06, 2.72376360044e-06, 2.41902398557e-06, 2.12747227124e-06, 1.85383657936e-06, 1.91547064787e-06, 1.7612596821e-06, 1.29205056965e-06, 1.34697086196e-06, 1.04755224584e-06, 6.72625560583e-07, 7.0366172622e-07, 6.68321149533e-07, 5.06154719915e-07],
        "dmean2": [0.00339499535039, 0.00225709122606, 0.00115177687258, 0.000565440859646, 0.000343500520103, 0.000271640339633, 0.000211988110095, 0.000276608712738, 0.000236207153648, 0.000203879884793, 0.000106072780909, 6.70553999953e-05, 5.88790135225e-05, 5.44384020031e-05, 4.82657669636e-05, 6.14197197137e-05, 4.7582143452e-05, 4.08465821238e-05, 2.96709677059e-05, 1.87779387488e-05, 1.66895970324e-05, 2.31605390582e-05, 1.62170108524e-05, 9.75343118625e-06, 7.4151548688e-06, 7.81213111622e-06, 6.64770686853e-06, 4.27201939601e-06, 3.82861526305e-06, 3.34404535351e-06, 2.87425336865e-06, 2.91239075523e-06, 2.67902328233e-06, 2.01242642106e-06, 2.0506608962e-06, 1.60887475431e-06, 1.0430991324e-06, 1.09373695523e-06, 1.0140527138e-06, 7.56965107485e-07],
        "dvar": [4.74475309602e-05, 1.43940987982e-05, 3.95848064727e-06, 5.5906656371e-07, 1.86074913699e-07, 1.2387947379e-07, 6.45103526153e-08, 1.2253056525e-07, 1.13660291845e-07, 1.00325330266e-07, 2.15273221471e-08, 1.02778887623e-08, 6.73699185327e-09, 6.08922912093e-09, 8.43186143129e-09, 8.98889229717e-09, 5.02454566842e-09, 4.88422813305e-09, 3.03890113074e-09, 1.23999788215e-09, 1.09613873533e-09, 9.24799015145e-10, 5.2200621603e-10, 2.53029264208e-10, 1.11768955202e-10, 1.17199860927e-10, 8.13038941727e-11, 6.25078808159e-11, 4.68662816888e-11, 3.72062484988e-11, 2.27736215302e-11, 2.2275226802e-11, 2.4665994941e-11, 2.84746011492e-11, 4.84248717514e-11, 2.71677957908e-11, 3.11651030503e-12, 2.61331624743e-12, 2.23684959444e-12, 1.47803514219e-12],
        "dvar2": [9.23671032069e-05, 3.88237531297e-05, 1.07143896457e-05, 1.49038362451e-06, 5.1618985708e-07, 3.11832707212e-07, 1.71987124986e-07, 2.83879700191e-07, 2.80075454384e-07, 2.44131371119e-07, 4.94230398829e-08, 2.6440680756e-08, 1.69906186898e-08, 1.4695091366e-08, 2.24370690916e-08, 2.47930902475e-08, 1.25150423358e-08, 1.19743974736e-08, 7.21872872589e-09, 3.34342309394e-09, 2.84464607425e-09, 2.27679697318e-09, 1.34601985113e-09, 6.12269013267e-10, 2.61768412502e-10, 2.76847628156e-10, 2.11698117369e-10, 1.41468767256e-10, 1.16170975617e-10, 9.27171533993e-11, 5.1310695276e-11, 4.70705453781e-11, 5.8667862235e-11, 7.22254131502e-11, 1.19796339515e-10, 6.63588767269e-11, 6.65610145126e-12, 6.09945904548e-12, 5.05929196107e-12, 3.23882674153e-12],
        "max": [0.0876316875219, 0.0503721684217, 0.0202505681664, 0.0138895418495, 0.00583140412346, 0.00638826843351, 0.00528165604919, 0.00651485752314, 0.00677358033136, 0.00539603643119, 0.00278416485526, 0.00250531197526, 0.00158011750318, 0.00142838770989, 0.0020002364181, 0.00202105566859, 0.00190693163313, 0.00174891750794, 0.00197324645706, 0.000921904982533, 0.000986270606518, 0.000609331415035, 0.000434851535829, 0.000362509599654, 0.000143869285239, 0.000231204816373, 0.000224002273171, 0.000414425652707, 0.000263407535385, 0.000245701608947, 0.000141979471664, 0.000187388446648, 0.000217231296119, 0.000205783377169, 0.000330943585141, 0.000213524413994, 6.00505882176e-05, 3.12719166686e-05, 2.8208065487e-05, 2.02201754291e-05],
        "mean": [0.00363349216059, 0.0022505116649, 0.000923388230149, 0.000596099533141, 0.000401348341256, 0.000334193842718, 0.000254219252383, 0.000345883192495, 0.000287353934254, 0.000225334224524, 0.000129118081531, 7.02331017237e-05, 6.04472661507e-05, 5.61663800909e-05, 4.9460115406e-05, 6.00109451625e-05, 4.88789773954e-05, 3.78120639652e-05, 2.90601128654e-05, 1.90204045794e-05, 1.83066440513e-05, 2.50165776379e-05, 1.75536697498e-05, 1.07771829789e-05, 8.39372933115e-06, 9.38084849622e-06, 8.08309778222e-06, 5.2007726481e-06, 4.44554279966e-06, 3.93024311052e-06, 3.70104430658e-06, 3.84126497011e-06, 3.49224001184e-06, 2.3614913971e-06, 2.36140112975e-06, 1.81459449777e-06, 1.29597970044e-06, 1.35910443078e-06, 1.2886694094e-06, 9.16599731227e-07],
        "median": [0.000456180947367, 0.000559599197004, 0.000307085429085, 0.000300310988678, 0.000183050375199, 0.000122814628412, 0.000112923167762, 0.000100232267869, 7.80603950261e-05, 5.89083247178e-05, 3.76656171284e-05, 2.16785210796e-05, 1.56053883984e-05, 1.14473823487e-05, 8.15374914964e-06, 9.91776869341e-06, 9.63019829214e-06, 7.26673533791e-06, 5.48029220226e-06, 4.46284138889e-06, 4.85100736114e-06, 4.9350669542e-06, 3.33235493599e-06, 1.80906499736e-06, 1.9802598672e-06, 2.09504423765e-06, 1.99217311092e-06, 1.10261066766e-06, 9.33045328111e-07, 1.21825939914e-06, 1.34166339194e-06, 1.40251631819e-06, 1.13867417895e-06, 7.43621399124e-07, 7.51233301344e-07, 5.91251477999e-07, 4.27222914823e-07, 3.98515481947e-07, 4.33100893815e-07, 3.17607884881e-07],
        "min": [2.24433846321e-24, 1.89923706072e-24, 1.85083018899e-24, 2.09644558171e-24, 3.8321714983e-24, 2.70479223485e-24, 2.15719181572e-24, 3.03897126646e-24, 4.55354022549e-24, 6.13943463491e-24, 3.67639119104e-24, 5.11889514258e-24, 4.44731418814e-24, 5.86134144429e-24, 4.40941257709e-24, 3.97483857073e-24, 3.60104038067e-24, 5.25801234094e-24, 4.47815352194e-24, 5.64664939906e-24, 6.40234895841e-24, 9.03870277657e-24, 4.4738191257e-24, 6.93255065585e-24, 5.50100950431e-24, 5.25026020482e-24, 6.19181460458e-24, 7.1486819778e-24, 6.89216728839e-24, 6.75191491919e-24, 6.64463299152e-24, 5.07723894805e-24, 7.82056979913e-24, 8.19618828574e-24, 6.23898533127e-24, 7.10684631741e-24, 6.865996039e-24, 6.59656887986e-24, 7.1533331017e-24, 7.79169196798e-24],
        "var": [8.98774451343e-05, 1.84151558642e-05, 3.48850949194e-06, 8.26724715353e-07, 3.34658295742e-07, 2.51754016745e-07, 1.34125258455e-07, 3.50701697016e-07, 2.7511555345e-07, 2.11229718161e-07, 5.41268718734e-08, 2.0959886271e-08, 1.34131017404e-08, 1.38264875105e-08, 1.92786355768e-08, 1.89846165455e-08, 1.0947720952e-08, 7.56488915954e-09, 5.14166398347e-09, 2.09966777298e-09, 1.80900927571e-09, 2.01465244487e-09, 1.02592079276e-09, 5.25919030547e-10, 2.48631198962e-10, 2.61956761838e-10, 1.73911954282e-10, 1.10943997045e-10, 7.42317041169e-11, 6.0994598261e-11, 4.26064357406e-11, 4.70249568452e-11, 4.55658011322e-11, 3.71283802314e-11, 6.8326094782e-11, 3.5213044286e-11, 6.00581129967e-12, 5.5162983556e-12, 4.95329081571e-12, 2.90141933916e-12]
    },
    "mfcc": {
        "mean": [-699.100402832, 121.811225891, 12.9965953827, 14.6472320557, 1.20412671566, 3.35419726372, -2.44966650009, 2.29794740677, 2.79322385788, 2.55443572998, 3.74361157417, -0.176596298814, -2.06040000916],
        "cov": [[21490.1640625, -1535.31567383, -317.34765625, 744.917602539, 236.29788208, 86.8175964355, -204.045852661, 123.128173828, 33.7201347351, 104.04133606, 247.330718994, 251.86126709, 217.538513184], [-1535.31567383, 1634.68017578, 14.9607372284, -48.4636917114, -6.81032991409, 13.8323373795, 125.887580872, 16.1456451416, 14.966545105, -11.7317209244, -4.86188602448, 19.7070655823, 11.6084651947], [-317.34765625, 14.9607372284, 1050.6895752, 308.531646729, 161.654968262, 94.0297012329, 33.7106552124, 4.24228668213, 37.5660743713, -31.2771377563, -50.3954849243, -34.8362503052, -89.2728805542], [744.917602539, -48.4636917114, 308.531646729, 486.562957764, 223.166168213, 110.693382263, 70.465675354, 35.5787315369, 40.1717224121, 21.2674999237, -13.0304908752, 20.9918308258, -6.85330343246], [236.29788208, -6.81032991409, 161.654968262, 223.166168213, 345.6953125, 77.4694290161, 24.8518600464, 11.2325296402, 32.6212997437, 35.3562736511, -1.65799081326, -1.00559520721, -11.3363380432], [86.8175964355, 13.8323373795, 94.0297012329, 110.693382263, 77.4694290161, 208.109008789, 107.340232849, 39.7411499023, 25.7158794403, 14.7789840698, 23.913476944, 32.1851577759, 17.5128498077], [-204.045852661, 125.887580872, 33.7106552124, 70.465675354, 24.8518600464, 107.340232849, 272.008666992, 71.5768737793, 32.317440033, 33.0757675171, 31.4695701599, 51.3399353027, 39.4661521912], [123.128173828, 16.1456451416, 4.24228668213, 35.5787315369, 11.2325296402, 39.7411499023, 71.5768737793, 160.823898315, 52.2515182495, 28.6325511932, 21.46925354, 5.2967133522, 21.4112491608], [33.7201347351, 14.966545105, 37.5660743713, 40.1717224121, 32.6212997437, 25.7158794403, 32.317440033, 52.2515182495, 123.860435486, 52.9778594971, 25.7123699188, 6.08587789536, -7.15782690048], [104.04133606, -11.7317209244, -31.2771377563, 21.2674999237, 35.3562736511, 14.7789840698, 33.0757675171, 28.6325511932, 52.9778594971, 115.926292419, 46.9774055481, 12.3574514389, -8.95440101624], [247.330718994, -4.86188602448, -50.3954849243, -13.0304908752, -1.65799081326, 23.913476944, 31.4695701599, 21.46925354, 25.7123699188, 46.9774055481, 104.024093628, 38.3285675049, 14.8617200851], [251.86126709, 19.7070655823, -34.8362503052, 20.9918308258, -1.00559520721, 32.1851577759, 51.3399353027, 5.2967133522, 6.08587789536, 12.3574514389, 38.3285675049, 102.638450623, 60.0924377441], [217.538513184, 11.6084651947, -89.2728805542, -6.85330343246, -11.3363380432, 17.5128498077, 39.4661521912, 21.4112491608, -7.15782690048, -8.95440101624, 14.8617200851, 60.0924377441, 145.142974854]],
        "icov": [[5.86257665418e-05, 4.50155675935e-05, 3.6102028389e-05, -0.000129307372845, 1.43760644278e-05, 9.35840034799e-06, 9.44788262132e-05, -5.19498898939e-05, 2.42608584813e-05, 1.32447166834e-05, -0.000127715189592, -9.32765033212e-05, -3.96916548198e-05], [4.50155675935e-05, 0.00068310945062, 3.78577783522e-06, 5.42159905308e-05, -6.55664043734e-05, 0.000117043367936, -0.000322398554999, 9.63745333138e-06, -0.000109924949356, 0.000182763338671, 7.72997950094e-08, -0.000155149813509, 1.98658108275e-05], [3.6102028389e-05, 3.78577783522e-06, 0.00133941264357, -0.000790912657976, -9.00494560483e-05, -0.000262124784058, -1.75525638042e-05, 7.59660251788e-05, -0.000398538948502, 0.000682036683429, 0.000176038738573, 6.22755978839e-05, 0.000728848797735], [-0.000129307372845, 5.42159905308e-05, -0.000790912657976, 0.00395077792928, -0.00183786742855, -0.000682414742187, -0.000488420133479, -0.000286757102003, -0.000235403946135, -0.000232476217207, 0.00119958515279, -0.000838712963741, 0.000201916554943], [1.43760644278e-05, -6.55664043734e-05, -9.00494560483e-05, -0.00183786742855, 0.00440764473751, -0.0009202833171, 0.000451320316643, 0.000392980815377, -0.000178544287337, -0.00122666591778, 0.000143313940498, 0.000664177874569, -0.000258003652561], [9.35840034799e-06, 0.000117043367936, -0.000262124784058, -0.000682414742187, -0.0009202833171, 0.00706845894456, -0.00222594919614, -0.000438898830907, -0.000262005749391, 0.000843797402922, -0.00114875729196, -0.000735276727937, -1.03968732219e-05], [9.44788262132e-05, -0.000322398554999, -1.75525638042e-05, -0.000488420133479, 0.000451320316643, -0.00222594919614, 0.00584190571681, -0.00178395153489, 0.000274297228316, -0.00106401275843, -4.72454448754e-05, -0.00179618247785, -0.000474783271784], [-5.19498898939e-05, 9.63745333138e-06, 7.59660251788e-05, -0.000286757102003, 0.000392980815377, -0.000438898830907, -0.00178395153489, 0.00843021459877, -0.00297496747226, -0.000219714987907, -0.000718907278497, 0.00219303648919, -0.00155922886916], [2.42608584813e-05, -0.000109924949356, -0.000398538948502, -0.000235403946135, -0.000178544287337, -0.000262005749391, 0.000274297228316, -0.00297496747226, 0.0115854777396, -0.00433684140444, -0.000565001391806, -0.000332394178258, 0.000597393081989], [1.32447166834e-05, 0.000182763338671, 0.000682036683429, -0.000232476217207, -0.00122666591778, 0.000843797402922, -0.00106401275843, -0.000219714987907, -0.00433684140444, 0.0135560734197, -0.00483342027292, -4.94709711347e-05, 0.00163600686938], [-0.000127715189592, 7.72997950094e-08, 0.000176038738573, 0.00119958515279, 0.000143313940498, -0.00114875729196, -4.72454448754e-05, -0.000718907278497, -0.000565001391806, -0.00483342027292, 0.0145287383348, -0.00470430776477, 0.00075901276432], [-9.32765033212e-05, -0.000155149813509, 6.22755978839e-05, -0.000838712963741, 0.000664177874569, -0.000735276727937, -0.00179618247785, 0.00219303648919, -0.000332394178258, -4.94709711347e-05, -0.00470430776477, 0.0164482761174, -0.00589131098241], [-3.96916548198e-05, 1.98658108275e-05, 0.000728848797735, 0.000201916554943, -0.000258003652561, -1.03968732219e-05, -0.000474783271784, -0.00155922886916, 0.000597393081989, 0.00163600686938, 0.00075901276432, -0.00589131098241, 0.0102375103161]]
    },
    "spectral_contrast_coeffs": {
        "dmean": [0.049052849412, 0.0466721318662, 0.0388514883816, 0.0305281300098, 0.0217869188637, 0.0171890836209],
        "dmean2": [0.0797138214111, 0.0754930898547, 0.0620810799301, 0.04883325845, 0.0339733622968, 0.026876764372],
        "dvar": [0.00172704271972, 0.001550254412, 0.0010953778401, 0.000709408952389, 0.000408677908126, 0.000252879573964],
        "dvar2": [0.00421935133636, 0.00381985423155, 0.00254185032099, 0.00164460379165, 0.00084619759582, 0.00055676617194],
        "max": [-0.30809789896, -0.400595098734, -0.406722247601, -0.527883350849, -0.564031898975, -0.56402105093],
        "mean": [-0.667178034782, -0.741765618324, -0.768051803112, -0.789704561234, -0.801214456558, -0.77775323391],
        "median": [-0.667661547661, -0.748882293701, -0.776428043842, -0.799488902092, -0.806342840195, -0.775867760181],
        "min": [-0.973357081413, -0.974677324295, -0.977605879307, -0.965413153172, -0.964425265789, -0.96322709322],
        "var": [0.00924575421959, 0.00725201517344, 0.00662154657766, 0.00464157806709, 0.00340166757815, 0.00218359543942]
    },
    "spectral_contrast_valleys": {
        "dmean": [0.405348777771, 0.384553730488, 0.344150930643, 0.306522488594, 0.267249524593, 0.304659485817],
        "dmean2": [0.640423357487, 0.60632032156, 0.53921186924, 0.451666384935, 0.372858941555, 0.39265191555],
        "dvar": [0.174190416932, 0.173288628459, 0.148234948516, 0.13941052556, 0.132406115532, 0.18064892292],
        "dvar2": [0.336747944355, 0.348377466202, 0.286197900772, 0.238722205162, 0.216922387481, 0.29506444931],
        "max": [-4.95237350464, -4.50450372696, -5.09008312225, -5.77889347076, -5.67648029327, -7.702729702],
        "mean": [-7.75616645813, -7.09601926804, -7.83504152298, -8.28238201141, -8.3535823822, -10.6391124725],
        "median": [-7.20753526688, -6.75861644745, -7.55755233765, -8.03382301331, -8.02520942688, -9.86361694336],
        "min": [-27.970413208, -27.7595081329, -27.4738521576, -27.4390106201, -27.4297962189, -27.3851623535],
        "var": [3.46006965637, 2.6380777359, 2.27638745308, 2.42680859566, 3.07268953323, 3.81864929199]
    }
},
"metadata": {
    "audio_properties": {
        "analysis_sample_rate": 44100,
        "bit_rate": 192024,
        "equal_loudness": 0,
        "length": 190.679977417,
        "lossless": 0,
        "replay_gain": -10.8585720062,
        "sample_rate": 48000,
        "codec": "mp3",
        "downmix": "mix",
        "md5_encoded": "3577d3db8f2ffdf4404adcf975cd04d6"
    },
    "tags": {
        "file_name": "United Kingdom_My Last Breath_James Newman.mp3",
        "encoding": ["Lavf58.45.100"]
    },
    "version": {
        "essentia": "2.1-beta2",
        "essentia_git_sha": "v2.1_beta2",
        "extractor": "music 1.0"
    }
},
"rhythm": {
    "beats_count": 316,
    "beats_loudness": {
        "dmean": 0.0252483561635,
        "dmean2": 0.0455022267997,
        "dvar": 0.00101650424767,
        "dvar2": 0.00280142528936,
        "max": 0.27427649498,
        "mean": 0.0687080994248,
        "median": 0.0634774938226,
        "min": 4.30275491681e-07,
        "var": 0.00413693627343
    },
    "bpm": 89.4109191895,
    "bpm_histogram_first_peak_bpm": {
        "dmean": 0,
        "dmean2": 0,
        "dvar": 0,
        "dvar2": 0,
        "max": 89,
        "mean": 89,
        "median": 89,
        "min": 89,
        "var": 0
    },
    "bpm_histogram_first_peak_spread": {
        "dmean": 0,
        "dmean2": 0,
        "dvar": 0,
        "dvar2": 0,
        "max": 0.34597158432,
        "mean": 0.34597158432,
        "median": 0.34597158432,
        "min": 0.34597158432,
        "var": 0
    },
    "bpm_histogram_first_peak_weight": {
        "dmean": 0,
        "dmean2": 0,
        "dvar": 0,
        "dvar2": 0,
        "max": 0.438095241785,
        "mean": 0.438095241785,
        "median": 0.438095241785,
        "min": 0.438095241785,
        "var": 0
    },
    "bpm_histogram_second_peak_bpm": {
        "dmean": 0,
        "dmean2": 0,
        "dvar": 0,
        "dvar2": 0,
        "max": 133,
        "mean": 133,
        "median": 133,
        "min": 133,
        "var": 0
    },
    "bpm_histogram_second_peak_spread": {
        "dmean": 0,
        "dmean2": 0,
        "dvar": 0,
        "dvar2": 0,
        "max": 0.294117629528,
        "mean": 0.294117629528,
        "median": 0.294117629528,
        "min": 0.294117629528,
        "var": 0
    },
    "bpm_histogram_second_peak_weight": {
        "dmean": 0,
        "dmean2": 0,
        "dvar": 0,
        "dvar2": 0,
        "max": 0.0761904790998,
        "mean": 0.0761904790998,
        "median": 0.0761904790998,
        "min": 0.0761904790998,
        "var": 0
    },
    "danceability": 1.07117378712,
    "onset_rate": 3.29848027229,
    "beats_loudness_band_ratio": {
        "dmean": [0.175160691142, 0.119068339467, 0.112753078341, 0.0564878024161, 0.0427518263459, 0.0773768052459],
        "dmean2": [0.31211400032, 0.210855782032, 0.204779848456, 0.099729090929, 0.0769426822662, 0.151436507702],
        "dvar": [0.0339456349611, 0.023572832346, 0.0245908014476, 0.00991878192872, 0.00770325493068, 0.0394242741168],
        "dvar2": [0.086369805038, 0.067405551672, 0.0773964449763, 0.0273188967258, 0.0222156513482, 0.121712192893],
        "max": [0.993564486504, 0.851841390133, 0.893289506435, 0.851566255093, 0.835020124912, 0.986761987209],
        "mean": [0.594971597195, 0.154828265309, 0.133154377341, 0.0757860839367, 0.0397418402135, 0.0512856766582],
        "median": [0.69025182724, 0.0725853145123, 0.0835274904966, 0.0363945290446, 0.0209745448083, 0.0145606752485],
        "min": [0.000262614892563, 0.00158923445269, 5.45836774108e-05, 5.22965929122e-05, 1.25570022647e-05, 5.22262507729e-06],
        "var": [0.0977786928415, 0.0396723970771, 0.0244577806443, 0.0157888643444, 0.00564678153023, 0.0221152342856]
    },
    "beats_position": [0.429569154978, 0.882358253002, 1.3235373497, 1.77632653713, 2.22911548615, 2.68190479279, 3.16952371597, 3.65714287758, 4.14476203918, 4.72526073456, 5.2941493988, 5.86303853989, 6.35065746307, 6.82666635513, 7.31428575516, 7.75546455383, 8.19664382935, 8.64943313599, 9.10222244263, 9.55501079559, 10.0078001022, 10.4605894089, 10.9133787155, 11.3661680222, 11.8189563751, 12.1788663864, 12.5503854752, 12.9102945328, 13.2818136215, 13.6533327103, 14.0132427216, 14.3731517792, 14.7214508057, 15.0697498322, 15.4296598434, 15.7779588699, 16.1378688812, 16.5442180634, 16.9621772766, 17.3801364899, 17.786485672, 18.181224823, 18.5875740051, 18.9939231873, 19.4118824005, 19.8298416138, 20.247800827, 20.6773700714, 21.1185474396, 21.5713367462, 22.0241260529, 22.4885253906, 22.9413146973, 23.405714035, 23.7772331238, 24.1255321503, 24.4854412079, 24.8569602966, 25.2052612305, 25.553560257, 25.8902492523, 26.2269382477, 26.563627243, 26.8887062073, 27.2137870789, 27.5504760742, 27.8871650696, 28.2238540649, 28.5605430603, 28.897233963, 29.2339229584, 29.5706119537, 30.0234012604, 30.476190567, 30.9289798737, 31.3817672729, 31.8345565796, 32.2873458862, 32.7401351929, 33.1813163757, 33.6224937439, 34.0636711121, 34.5048522949, 34.9576416016, 35.4104309082, 35.9212684631, 36.4204978943, 36.9197273254, 37.5931053162, 38.2664833069, 38.9398651123, 39.613243103, 40.2866210938, 40.9599990845, 41.6333770752, 42.3067550659, 42.9801368713, 43.6535148621, 44.3268928528, 44.9886627197, 45.650428772, 46.3238105774, 46.9971885681, 47.6705665588, 48.3439445496, 49.0057144165, 49.6674804688, 50.3408622742, 51.0142402649, 51.6876182556, 52.3609962463, 53.0343742371, 53.696144104, 54.3579139709, 55.0312919617, 55.7046699524, 56.3664398193, 57.0282058716, 57.701587677, 58.3749656677, 59.0483436584, 59.7101135254, 60.3718795776, 61.0452613831, 61.7186393738, 62.3920173645, 63.0653953552, 63.7387733459, 64.4121551514, 65.0739212036, 65.7356872559, 66.409072876, 67.0824508667, 67.7558288574, 68.4292068481, 69.0909729004, 69.7527389526, 70.4261245728, 71.0995025635, 71.7728805542, 72.4346466064, 73.1080245972, 73.7697982788, 74.4431762695, 75.1165542603, 75.789932251, 76.4633102417, 77.1250762939, 77.7868499756, 78.4602279663, 79.133605957, 79.8069839478, 80.4803619385, 81.1537399292, 81.8155059814, 82.4772796631, 83.1506576538, 83.8124237061, 84.4741897583, 85.1475753784, 85.8209533691, 86.4943313599, 87.1677093506, 87.8410873413, 88.514465332, 89.1878433228, 89.8612213135, 90.5345993042, 91.1963729858, 91.8697509766, 92.5315170288, 93.2048950195, 93.8782730103, 94.551651001, 95.2250289917, 95.8984146118, 96.5601806641, 97.2219467163, 97.8837203979, 98.5454864502, 99.2188644409, 99.8922424316, 100.565620422, 101.238998413, 101.900772095, 102.562538147, 103.235916138, 103.909294128, 104.582672119, 105.244445801, 105.906211853, 106.579589844, 107.252967834, 107.926345825, 108.599723816, 109.273101807, 109.934875488, 110.596641541, 111.270019531, 111.943397522, 112.616775513, 113.290153503, 113.951927185, 114.613693237, 115.287071228, 115.960449219, 116.633827209, 117.3072052, 117.968978882, 118.630744934, 119.304122925, 119.977500916, 120.650878906, 121.324264526, 121.986030579, 122.647796631, 123.321174622, 123.994552612, 124.667930603, 125.341316223, 126.003082275, 126.664848328, 127.338226318, 128.011611938, 128.6849823, 129.35836792, 130.008529663, 130.681900024, 131.355285645, 132.017044067, 132.678817749, 133.352203369, 134.02557373, 134.698959351, 135.372329712, 136.045715332, 136.719085693, 137.404083252, 138.089065552, 138.77406311, 139.45904541, 140.213699341, 140.968338013, 141.734603882, 142.500854492, 143.209060669, 143.917282104, 144.613876343, 145.310470581, 146.018676758, 146.726898193, 147.411880493, 148.096862793, 148.770248413, 149.443618774, 150.117004395, 150.778778076, 151.440536499, 152.113922119, 152.78729248, 153.460678101, 154.134063721, 154.795822144, 155.457595825, 156.130966187, 156.804351807, 157.477722168, 158.151107788, 158.81288147, 159.474639893, 160.148025513, 160.821395874, 161.494781494, 162.168167114, 162.829925537, 163.491699219, 164.16506958, 164.8384552, 165.51184082, 166.185211182, 166.846984863, 167.508743286, 168.182128906, 168.855514526, 169.528884888, 170.190658569, 170.852416992, 171.525802612, 172.199172974, 172.872558594, 173.545944214, 174.219314575, 174.869476318, 175.554458618, 176.251068115, 176.97088623, 177.702316284, 178.398910522, 179.118728638, 179.826934814, 180.535140991, 181.243347168, 181.951568604, 182.648162842, 183.34475708, 184.041351318, 184.633468628, 185.21395874, 185.759628296, 186.305297852, 186.862579346, 187.454696655, 188.046798706, 188.638900757, 189.242630005, 189.834732056]
},
"tonal": {
    "chords_changes_rate": 0.105429753661,
    "chords_number_rate": 0.0043827611953,
    "chords_strength": {
        "dmean": 0.0107168285176,
        "dmean2": 0.0114610018209,
        "dvar": 9.58687160164e-05,
        "dvar2": 0.000131794207846,
        "max": 0.740302443504,
        "mean": 0.518554210663,
        "median": 0.519045710564,
        "min": 0.205660283566,
        "var": 0.00900485459715
    },
    "hpcp_entropy": {
        "dmean": 0.601228833199,
        "dmean2": 1.00258886814,
        "dvar": 0.249113678932,
        "dvar2": 0.675536096096,
        "max": 4.41096067429,
        "mean": 2.15171766281,
        "median": 2.15163803101,
        "min": 0,
        "var": 0.567205667496
    },
    "key_strength": 0.710446476936,
    "tuning_diatonic_strength": 0.622435986996,
    "tuning_equal_tempered_deviation": 0.144520178437,
    "tuning_frequency": 434.193115234,
    "tuning_nontempered_energy_ratio": 0.842555642128,
    "hpcp": {
        "dmean": [0.0951259285212, 0.0964073389769, 0.110533162951, 0.117064803839, 0.130490675569, 0.144689828157, 0.139415964484, 0.104349270463, 0.0801096260548, 0.082535803318, 0.0985901653767, 0.140216380358, 0.134037047625, 0.0959262698889, 0.0747834146023, 0.0740240439773, 0.0928912386298, 0.121337622404, 0.124661169946, 0.108118489385, 0.0999603271484, 0.0989324748516, 0.0883234143257, 0.138805568218, 0.208581164479, 0.16406224668, 0.167871415615, 0.173956766725, 0.128961920738, 0.0896464586258, 0.116874724627, 0.165244176984, 0.185454428196, 0.17184881866, 0.134386211634, 0.109164513648],
        "dmean2": [0.16970513761, 0.171337917447, 0.191311106086, 0.206456288695, 0.235852614045, 0.250912308693, 0.238781794906, 0.183521091938, 0.143892258406, 0.149197116494, 0.174205049872, 0.234525114298, 0.223557323217, 0.168185994029, 0.134985595942, 0.134398013353, 0.16492216289, 0.208026006818, 0.214708015323, 0.190657034516, 0.172693029046, 0.172591164708, 0.156171679497, 0.248763084412, 0.379149407148, 0.291936963797, 0.282521545887, 0.293613702059, 0.224125728011, 0.161441102624, 0.213488385081, 0.295055508614, 0.326450496912, 0.293413192034, 0.236418277025, 0.195462867618],
        "dvar": [0.0328911840916, 0.0311901718378, 0.0313670299947, 0.0369499027729, 0.0421001017094, 0.0471727624536, 0.0459499210119, 0.0327730849385, 0.0278213247657, 0.0302688647062, 0.0285609494895, 0.0413713939488, 0.0385317057371, 0.0252608582377, 0.028101682663, 0.0266403108835, 0.0289368927479, 0.0385987982154, 0.0379220806062, 0.0310197528452, 0.0304442048073, 0.0328177437186, 0.0252038557082, 0.0381645560265, 0.0921735391021, 0.0379840284586, 0.0466862097383, 0.0534281730652, 0.0342805162072, 0.0280314963311, 0.0427897386253, 0.0611552633345, 0.063453964889, 0.0514510497451, 0.0418516397476, 0.0412978939712],
        "dvar2": [0.0882304981351, 0.085531488061, 0.0830125659704, 0.102530151606, 0.117472968996, 0.120822414756, 0.11632668972, 0.0878565311432, 0.0764690935612, 0.0851918235421, 0.0784125551581, 0.102970309556, 0.0939030572772, 0.0695721656084, 0.077194429934, 0.0735159516335, 0.0784959420562, 0.0993644595146, 0.0956757441163, 0.0856360569596, 0.0769670903683, 0.0818364694715, 0.0704566687346, 0.107167668641, 0.253883868456, 0.104526594281, 0.113687127829, 0.120539836586, 0.0928577184677, 0.0799096077681, 0.115679688752, 0.168540522456, 0.163531169295, 0.131487980485, 0.112414628267, 0.113071650267],
        "max": [1, 1, 1, 1, 1, 1, 1, 1, 1, 1, 1, 1, 1, 1, 1, 1, 1, 1, 1, 1, 1, 1, 1, 1, 1, 1, 1, 1, 1, 1, 1, 1, 1, 1, 1, 1],
        "mean": [0.0859241336584, 0.0936131551862, 0.125180333853, 0.123349905014, 0.125667974353, 0.192153543234, 0.184562891722, 0.104634605348, 0.0768716707826, 0.0810824856162, 0.113739199936, 0.222308367491, 0.222359955311, 0.106833964586, 0.0675503984094, 0.0670722946525, 0.0908617153764, 0.148298129439, 0.14799824357, 0.112495712936, 0.141409695148, 0.13518024981, 0.0853963792324, 0.161753118038, 0.248771727085, 0.206105425954, 0.283934026957, 0.309298276901, 0.148311153054, 0.0799563750625, 0.106801643968, 0.169200852513, 0.253118991852, 0.234632775187, 0.140217468143, 0.10070771724],
        "median": [0.0133209694177, 0.026454988867, 0.045543409884, 0.0471672676504, 0.0456465557218, 0.0635768771172, 0.0561809241772, 0.0253594536334, 0.0114986225963, 0.0103524867445, 0.0340920723975, 0.0741139650345, 0.0678417906165, 0.036194305867, 0.0115934154019, 0.0124893859029, 0.0275426786393, 0.0481696762145, 0.0495759323239, 0.0517152175307, 0.039075654, 0.0264117028564, 0.0252591166645, 0.0528659038246, 0.0585878640413, 0.101857960224, 0.123641319573, 0.125048801303, 0.0565797016025, 0.0127120353281, 0.0138146085665, 0.037684943527, 0.0911365970969, 0.0939996391535, 0.0473526977003, 0.0138965146616],
        "min": [0, 0, 0, 0, 0, 0, 0, 0, 0, 0, 0, 0, 0, 0, 0, 0, 0, 0, 0, 0, 0, 0, 0, 0, 0, 0, 0, 0, 0, 0, 0, 0, 0, 0, 0, 0],
        "var": [0.0323856472969, 0.0301780048758, 0.0355652086437, 0.0348336286843, 0.0389396622777, 0.0765558257699, 0.0756578072906, 0.0353486686945, 0.0302762296051, 0.0325059890747, 0.0377329848707, 0.0865322798491, 0.0908603966236, 0.0271777659655, 0.0252032764256, 0.0228260904551, 0.0275214258581, 0.0539418384433, 0.0522890612483, 0.0286914985627, 0.0613771006465, 0.0639808475971, 0.0235548410565, 0.0459167324007, 0.119591549039, 0.055060133338, 0.106755211949, 0.127083018422, 0.0417570844293, 0.0271437894553, 0.0444499701262, 0.0686327442527, 0.101719923317, 0.0870781093836, 0.0460489615798, 0.0408977605402]
    },
    "chords_histogram": [14.0735330582, 3.67664957047, 6.16021442413, 10.5673236847, 1.53396642208, 6.30630636215, 5.72193813324, 2.97053813934, 4.94278049469, 1.31482839584, 11.5899686813, 0, 3.8227417469, 2.09398579597, 3.53055763245, 0.560019493103, 0.0486973449588, 0.0243486724794, 0.0243486724794, 1.46092033386, 5.4297542572, 3.99318242073, 9.25249576569, 0.900900900364],
    "thpcp": [1, 0.47950848937, 0.258508950472, 0.345303058624, 0.547047495842, 0.818365335464, 0.758597075939, 0.453340619802, 0.325600653887, 0.277803480625, 0.30266302824, 0.404723674059, 0.398805677891, 0.406300276518, 0.621256411076, 0.596714913845, 0.338296771049, 0.248535722494, 0.262149810791, 0.367733061314, 0.71875077486, 0.718917548656, 0.345407575369, 0.218398883939, 0.216853111982, 0.293767273426, 0.479466408491, 0.478496819735, 0.363712698221, 0.457195222378, 0.437054634094, 0.276097178459, 0.522968053818, 0.804310083389, 0.666364610195, 0.917994201183],
    "chords_key": "F#",
    "chords_scale": "major",
    "key_key": "F#",
    "key_scale": "major"
}
}